setup.py
pyrelic/__init__.py
pyrelic/application.py
pyrelic/base_client.py
pyrelic/client.py
pyrelic/exceptions.py
pyrelic/metric.py
pyrelic/server.py
pyrelic/threshold.py
pyrelic.egg-info/PKG-INFO
pyrelic.egg-info/SOURCES.txt
pyrelic.egg-info/dependency_links.txt
pyrelic.egg-info/requires.txt
pyrelic.egg-info/top_level.txt