Metadata-Version: 1.1
Name: pyrelic
Version: 0.8.0
Summary: Python API Wrapper for NewRelic API
Home-page: https://github.com/andrewgross/pyrelic
Author: Andrew Gross
Author-email: andrew.w.gross@gmail.com
License: GPL
Platform: UNKNOWN
Classifier: Development Status :: 3 - Alpha
Classifier: Intended Audience :: Developers
Classifier: License :: OSI Approved :: GNU General Public License v3 or later (GPLv3+)
Classifier: Natural Language :: English
Classifier: Operating System :: Microsoft
Classifier: Operating System :: POSIX
Classifier: Programming Language :: Python
Classifier: Programming Language :: Python :: 2.7
